baseten_benchmarks/__init__.py
baseten_benchmarks/benchmark_executor.py
baseten_benchmarks/data/books.txt
baseten_benchmarks/generic_rest_provider.py
baseten_benchmarks/input_handler.py
baseten_benchmarks/llm_benchmark.py
baseten_benchmarks/llm_provider.py
baseten_benchmarks/metrics_calculator.py
baseten_benchmarks/parse_args.py
baseten_benchmarks/request_handler.py
baseten_benchmarks/request_types.py
baseten_benchmarks/stream_handler.py
baseten_benchmarks-0.6.0.dist-info/METADATA
baseten_benchmarks-0.6.0.dist-info/WHEEL
baseten_benchmarks-0.6.0.dist-info/entry_points.txt
baseten_benchmarks-0.6.0.dist-info/RECORD
